netscript/__init__.py
netscript/script_server.py
netscript-1.1.dist-info/licenses/LICENSE
netscript-1.1.dist-info/METADATA
netscript-1.1.dist-info/WHEEL
netscript-1.1.dist-info/top_level.txt
netscript-1.1.dist-info/RECORD
