Metadata-Version: 2.4
Name: netscript
Version: 1.1
Summary: toml version
Author: Grey Liedtke
Author-email: grey.liedtke@gmail.com
License-Expression: MIT
Project-URL: Homepage, https://github.com/pypa/sampleproject
Project-URL: Issues, https://github.com/pypa/sampleproject/issues
Classifier: Programming Language :: Python :: 3
Classifier: Operating System :: OS Independent
Requires-Python: >=3.9
License-File: LICENSE
Dynamic: author
Dynamic: author-email
Dynamic: license-file
